app/__init__.py
app/_version.py
app/cli.py
app/config.py
app/api/__init__.py
app/api/api_client.py
app/dao/__init__.py
app/dao/new_email_dao.py
app/dao/new_email_interactive_dao.py
app/router/__init__.py
app/router/router.py
app/utils/__init__.py
app/utils/exceptions.py
app/utils/logger/__init__.py
app/utils/logger/logging_utils.py
test/__init__.py
test/test_api_client.py
test/test_cli.py
test/test_dao_interactive_cli.py
test/test_router.py
decy_tools-2.2.1.dist-info/LICENSE.txt
decy_tools-2.2.1.dist-info/METADATA
decy_tools-2.2.1.dist-info/WHEEL
decy_tools-2.2.1.dist-info/entry_points.txt
decy_tools-2.2.1.dist-info/top_level.txt
decy_tools-2.2.1.dist-info/RECORD
