Metadata-Version: 2.1
Name: decy-tools
Version: 2.2.1
Summary: CLI tool to utilize with Decypher automation 
Home-page: https://gitlab.com/decyphertech/decy-tools
Author: Jakson Wainwright
Author-email: jaxonawain@gmail.com
License: MIT
Keywords: decypher automation
Platform: UNKNOWN
Requires-Python: >=3.8.2
License-File: LICENSE.txt
Requires-Dist: requests (==2.26.0)
Requires-Dist: prompt-toolkit (==3.0.23)
Provides-Extra: build
Requires-Dist: wheel-0.37.0 ; extra == 'build'
Requires-Dist: black (==20.8b1) ; extra == 'build'
Provides-Extra: test
Requires-Dist: pytest (==6.2.2) ; extra == 'test'
Requires-Dist: pytest-cov (==2.11.1) ; extra == 'test'
Requires-Dist: toml (==0.10.2) ; extra == 'test'
